[
  {
    "type_general": "RPD",
    "dispatch_time": "11/08/2025 18:24",
    "box_no": "Precinct 2",
    "type_specific": "MENTAL SUBJECT , INVESTIGATE EMS",
    "street": "2200-BLK CHALFONT DR",
    "status": "Enroute",
    "cross_street": "",
    "nearest_intersection": "Chalfont Drive, Southside",
    "location_township": "Precinct 2",
    "lat": 37.4908816,
    "lng": -77.4654757
  },
  {
    "type_general": "RPD",
    "dispatch_time": "11/08/2025 19:55",
    "box_no": "Precinct 1",
    "type_specific": "ROBBERY , JUST OCCURRED/ IN-PROGRESS",
    "street": "1600-BLK MECHANICSVILLE TPKE",
    "status": "Arrived",
    "cross_street": "",
    "nearest_intersection": "Mechanicsville Turnpike",
    "location_township": "Precinct 1",
    "lat": 37.5493398,
    "lng": -77.4147445
  },
  {
    "type_general": "RPD",
    "dispatch_time": "11/09/2025 00:16",
    "box_no": "Precinct 3",
    "type_specific": "MENTAL SUBJECT , INVESTIGATE EMS",
    "street": "1100-BLK GROVE AVE",
    "status": "Arrived",
    "cross_street": "",
    "nearest_intersection": "Grove Avenue",
    "location_township": "Precinct 3",
    "lat": 37.5487219,
    "lng": -77.4554131
  },
  {
    "type_general": "RPD",
    "dispatch_time": "11/09/2025 00:52",
    "box_no": "Precinct 1",
    "type_specific": "CRASH , CITY PROPERTY",
    "street": "MECHANICSVILLE TPKE/E LABURNUM AVE HENR",
    "status": "Enroute",
    "cross_street": "",
    "nearest_intersection": "Mechanicsville Turnpike",
    "location_township": "Precinct 1",
    "lat": 37.5559863,
    "lng": -77.4101543
  },
  {
    "type_general": "RPD",
    "dispatch_time": "11/09/2025 02:48",
    "box_no": "Precinct 3",
    "type_specific": "DOMESTIC TROUBLE , INVESTIGATE - EMS",
    "street": "200-BLK ERICH RD",
    "status": "Arrived",
    "cross_street": "",
    "nearest_intersection": "Erich Road",
    "location_township": "Precinct 3",
    "lat": 37.50836,
    "lng": -77.500036
  },
  {
    "type_general": "RPD",
    "dispatch_time": "11/09/2025 03:22",
    "box_no": "Precinct 1",
    "type_specific": "ASSIST - OTHER AGENCY OR CALLER , CITIZEN",
    "street": "1700-BLK FAIRFIELD WAY",
    "status": "Arrived",
    "cross_street": "",
    "nearest_intersection": "Fairfield Way",
    "location_township": "Precinct 1",
    "lat": 37.5482872,
    "lng": -77.4226215
  },
  {
    "type_general": "RPD",
    "dispatch_time": "11/09/2025 03:22",
    "box_no": "Precinct 1",
    "type_specific": "ASSIST - OTHER AGENCY OR CALLER , CITIZEN",
    "street": "1700-BLK FAIRFIELD WAY",
    "status": "Arrived",
    "cross_street": "",
    "nearest_intersection": "Fairfield Way",
    "location_township": "Precinct 1",
    "lat": 37.5482872,
    "lng": -77.4226215
  },
  {
    "type_general": "RPD",
    "dispatch_time": "11/09/2025 04:35",
    "box_no": "Precinct 3",
    "type_specific": "BURGLAR ALARM , INVESTIGATE",
    "street": "1900-BLK W MAIN ST",
    "status": "Arrived",
    "cross_street": "",
    "nearest_intersection": "West Main Street",
    "location_township": "Precinct 3",
    "lat": 37.5489827,
    "lng": -77.4646467
  },
  {
    "type_general": "RPD",
    "dispatch_time": "11/09/2025 04:55",
    "box_no": "Precinct 1",
    "type_specific": "TRESPASSING , INVESTIGATE",
    "street": "3000-BLK NINE MILE RD",
    "status": "Arrived",
    "cross_street": "",
    "nearest_intersection": "Nine Mile Road",
    "location_township": "Precinct 1",
    "lat": 37.542062,
    "lng": -77.399754
  },
  {
    "type_general": "RPD",
    "dispatch_time": "11/09/2025 05:41",
    "box_no": "Precinct 2",
    "type_specific": "UNNECESSARY NOISE , INVESTIGATE",
    "street": "1000-BLK KINGSWAY RD",
    "status": "Arrived",
    "cross_street": "",
    "nearest_intersection": "Kingsway Road",
    "location_township": "Precinct 2",
    "lat": 37.4940853,
    "lng": -77.4998469
  },
  {
    "type_general": "RPD",
    "dispatch_time": "11/09/2025 05:43",
    "box_no": "Precinct 4",
    "type_specific": "DISABLE VEHICLE - HAZARD , INVESTIGATE",
    "street": "LL(-77:27:19.8029,37:32:34.1672): @DOWNTOWN EXPY EB BETWEEN TOLL PLAZA & BELVIDERE ST",
    "status": "Enroute",
    "cross_street": "",
    "nearest_intersection": "Downtown Expressway",
    "location_township": "Precinct 4",
    "lng": -77.45550080555556,
    "lat": 37.54282422222222
  },
  {
    "type_general": "RPD",
    "dispatch_time": "11/09/2025 05:58",
    "box_no": "Precinct 2",
    "type_specific": "HOTSPOT-CURVE , OFFICER INITATED",
    "street": "600-BLK W SOUTHSIDE PLZ",
    "status": "Dispatched",
    "cross_street": "",
    "nearest_intersection": "West Southside Plaza, Southside",
    "location_township": "Precinct 2",
    "lat": 37.5012106,
    "lng": -77.4784074
  },
  {
    "type_general": "RPD",
    "dispatch_time": "11/09/2025 05:58",
    "box_no": "Precinct 2",
    "type_specific": "HOTSPOT-CURVE , OFFICER INITATED",
    "street": "600-BLK W SOUTHSIDE PLZ",
    "status": "Arrived",
    "cross_street": "",
    "nearest_intersection": "West Southside Plaza, Southside",
    "location_township": "Precinct 2",
    "lat": 37.5012106,
    "lng": -77.4784074
  }
]