[
  {
    "type_general": "RPD",
    "dispatch_time": "12/16/2025 05:50",
    "box_no": "Precinct 4",
    "type_specific": "MENTAL SUBJECT , TDO / ECO",
    "street": "7700-BLK E PARHAM RD",
    "status": "Enroute",
    "cross_street": "",
    "nearest_intersection": "",
    "location_township": "Precinct 4",
    "lat": null,
    "lng": null
  },
  {
    "type_general": "RPD",
    "dispatch_time": "12/16/2025 08:04",
    "box_no": "Precinct 3",
    "type_specific": "TRESPASSING , INVESTIGATE",
    "street": "2900-BLK W CARY ST",
    "status": "Arrived",
    "cross_street": "",
    "nearest_intersection": "",
    "location_township": "Precinct 3",
    "lat": null,
    "lng": null
  },
  {
    "type_general": "RPD",
    "dispatch_time": "12/16/2025 09:46",
    "box_no": "Precinct 3",
    "type_specific": "MENTAL SUBJECT , TDO / ECO",
    "street": "7100-BLK JAHNKE RD",
    "status": "Enroute",
    "cross_street": "",
    "nearest_intersection": "",
    "location_township": "Precinct 3",
    "lat": null,
    "lng": null
  },
  {
    "type_general": "RPD",
    "dispatch_time": "12/16/2025 10:23",
    "box_no": "Precinct 3",
    "type_specific": "WANTED PERSON , INVESTIGATE",
    "street": "6800-BLK EVERGLADES DR",
    "status": "Arrived",
    "cross_street": "",
    "nearest_intersection": "",
    "location_township": "Precinct 3",
    "lat": null,
    "lng": null
  },
  {
    "type_general": "RPD",
    "dispatch_time": "12/16/2025 10:59",
    "box_no": "Precinct 3",
    "type_specific": "MENTAL SUBJECT , TDO / ECO",
    "street": "400-BLK MELMARK CT",
    "status": "Enroute",
    "cross_street": "",
    "nearest_intersection": "",
    "location_township": "Precinct 3",
    "lat": null,
    "lng": null
  },
  {
    "type_general": "RPD",
    "dispatch_time": "12/16/2025 11:19",
    "box_no": "Precinct 2",
    "type_specific": "PROSTITUTION , INVESTIGATE",
    "street": "3600-BLK ROSANELL LN",
    "status": "Arrived",
    "cross_street": "",
    "nearest_intersection": "",
    "location_township": "Precinct 2",
    "lat": null,
    "lng": null
  },
  {
    "type_general": "RPD",
    "dispatch_time": "12/16/2025 11:41",
    "box_no": "Precinct 4",
    "type_specific": "CRASH , PROPERTY DAMAGE",
    "street": "ALTAMONT AVE/MOORE ST RICH",
    "status": "Arrived",
    "cross_street": "",
    "nearest_intersection": "",
    "location_township": "Precinct 4",
    "lat": null,
    "lng": null
  },
  {
    "type_general": "RPD",
    "dispatch_time": "12/16/2025 11:56",
    "box_no": "Precinct 1",
    "type_specific": "D.O.A. , INVESTIGATE",
    "street": "1700-BLK N 29TH ST",
    "status": "Arrived",
    "cross_street": "",
    "nearest_intersection": "",
    "location_township": "Precinct 1",
    "lat": null,
    "lng": null
  },
  {
    "type_general": "RPD",
    "dispatch_time": "12/16/2025 12:06",
    "box_no": "Precinct 1",
    "type_specific": "CRASH , PROPERTY DAMAGE",
    "street": "NELSON ST/SALEM ST RICH",
    "status": "Arrived",
    "cross_street": "",
    "nearest_intersection": "",
    "location_township": "Precinct 1",
    "lat": null,
    "lng": null
  },
  {
    "type_general": "RPD",
    "dispatch_time": "12/16/2025 12:09",
    "box_no": "Precinct 2",
    "type_specific": "ASSIST FIRE DEPARTMENT , TRAFFIC AND/OR CROWD CONTROL",
    "street": "2500-BLK TITUS ST",
    "status": "Arrived",
    "cross_street": "",
    "nearest_intersection": "",
    "location_township": "Precinct 2",
    "lat": null,
    "lng": null
  },
  {
    "type_general": "RPD",
    "dispatch_time": "12/16/2025 12:11",
    "box_no": "Precinct 2",
    "type_specific": "ASSIST - OTHER AGENCY OR CALLER , CITIZEN",
    "street": "1700-BLK FAIRFIELD WAY",
    "status": "Arrived",
    "cross_street": "",
    "nearest_intersection": "",
    "location_township": "Precinct 2",
    "lat": null,
    "lng": null
  },
  {
    "type_general": "RPD",
    "dispatch_time": "12/16/2025 12:47",
    "box_no": "DPR",
    "type_specific": "LARCENY , DPR Call - Take a Report",
    "street": "4200-BLK SULGRAVE RD",
    "status": "Enroute",
    "cross_street": "",
    "nearest_intersection": "",
    "location_township": "DPR",
    "lat": null,
    "lng": null
  },
  {
    "type_general": "RPD",
    "dispatch_time": "12/16/2025 12:48",
    "box_no": "Precinct 3",
    "type_specific": "CRASH , PROPERTY DAMAGE",
    "street": "W CARY ST/S DOOLEY AVE RICH",
    "status": "Arrived",
    "cross_street": "",
    "nearest_intersection": "",
    "location_township": "Precinct 3",
    "lat": null,
    "lng": null
  },
  {
    "type_general": "RPD",
    "dispatch_time": "12/16/2025 12:59",
    "box_no": "Precinct 4",
    "type_specific": "FOUND PROPERTY , INVESTIGATE",
    "street": "800-BLK E MAIN ST",
    "status": "Enroute",
    "cross_street": "",
    "nearest_intersection": "",
    "location_township": "Precinct 4",
    "lat": null,
    "lng": null
  },
  {
    "type_general": "RPD",
    "dispatch_time": "12/16/2025 13:07",
    "box_no": "Precinct 1",
    "type_specific": "ASSIST FIRE DEPARTMENT , TRAFFIC AND/OR CROWD CONTROL",
    "street": "1500-BLK E MAIN ST",
    "status": "Arrived",
    "cross_street": "",
    "nearest_intersection": "",
    "location_township": "Precinct 1",
    "lat": null,
    "lng": null
  },
  {
    "type_general": "RPD",
    "dispatch_time": "12/16/2025 13:10",
    "box_no": "Precinct 2",
    "type_specific": "REFERRAL FROM NGO OR GO , OFFICER INITIATED",
    "street": "5700-BLK ROUTE 1",
    "status": "Enroute",
    "cross_street": "",
    "nearest_intersection": "",
    "location_township": "Precinct 2",
    "lat": null,
    "lng": null
  },
  {
    "type_general": "RPD",
    "dispatch_time": "12/16/2025 13:11",
    "box_no": "Precinct 2",
    "type_specific": "WELFARE CHECK , INVESTIGATE",
    "street": "3700-BLK E BROAD ROCK RD",
    "status": "Arrived",
    "cross_street": "",
    "nearest_intersection": "",
    "location_township": "Precinct 2",
    "lat": null,
    "lng": null
  },
  {
    "type_general": "RPD",
    "dispatch_time": "12/16/2025 13:11",
    "box_no": "Precinct 1",
    "type_specific": "DRUG/NARCOTICS OFFENSE , INVESTIGATE / OUTSIDE",
    "street": "1600-BLK HULL ST",
    "status": "Enroute",
    "cross_street": "",
    "nearest_intersection": "",
    "location_township": "Precinct 1",
    "lat": null,
    "lng": null
  },
  {
    "type_general": "RPD",
    "dispatch_time": "12/16/2025 13:15",
    "box_no": "Precinct 4",
    "type_specific": "ABANDONED VEHICLE , INVESTIGATE",
    "street": "N 6TH ST/E FRANKLIN ST RICH",
    "status": "Arrived",
    "cross_street": "",
    "nearest_intersection": "",
    "location_township": "Precinct 4",
    "lat": null,
    "lng": null
  },
  {
    "type_general": "RPD",
    "dispatch_time": "12/16/2025 13:16",
    "box_no": "Precinct 3",
    "type_specific": "MENTAL SUBJECT , MENTAL SUBJECT EMERGENT",
    "street": "5600-BLK JAHNKE RD",
    "status": "Enroute",
    "cross_street": "",
    "nearest_intersection": "",
    "location_township": "Precinct 3",
    "lat": null,
    "lng": null
  },
  {
    "type_general": "RPD",
    "dispatch_time": "12/16/2025 13:16",
    "box_no": "Precinct 4",
    "type_specific": "DOMESTIC TROUBLE , VIOLENT - EMS",
    "street": "200-BLK W BAKER ST",
    "status": "Arrived",
    "cross_street": "",
    "nearest_intersection": "",
    "location_township": "Precinct 4",
    "lat": null,
    "lng": null
  },
  {
    "type_general": "RPD",
    "dispatch_time": "12/16/2025 13:18",
    "box_no": "Precinct 1",
    "type_specific": "TRAFFIC STOP , OFFICER-INITIATED",
    "street": "2300-BLK ROSETTA ST",
    "status": "Arrived",
    "cross_street": "",
    "nearest_intersection": "",
    "location_township": "Precinct 1",
    "lat": 37.548743,
    "lng": -77.406126
  },
  {
    "type_general": "RPD",
    "dispatch_time": "12/16/2025 13:18",
    "box_no": "Precinct 1",
    "type_specific": "TRAFFIC STOP , OFFICER-INITIATED",
    "street": "2300-BLK ROSETTA ST",
    "status": "Arrived",
    "cross_street": "",
    "nearest_intersection": "",
    "location_township": "Precinct 1",
    "lat": null,
    "lng": null
  },
  {
    "type_general": "RPD",
    "dispatch_time": "12/16/2025 13:18",
    "box_no": "Precinct 1",
    "type_specific": "TRAFFIC STOP , OFFICER-INITIATED",
    "street": "2300-BLK ROSETTA ST",
    "status": "Arrived",
    "cross_street": "",
    "nearest_intersection": "Rosetta Street",
    "location_township": "Precinct 1",
    "lat": 37.548743,
    "lng": -77.406126
  },
  {
    "type_general": "RPD",
    "dispatch_time": "12/16/2025 13:28",
    "box_no": "Precinct 4",
    "type_specific": "DISORDERLY , INVESTIGATE",
    "street": "0-BLK W GRACE ST",
    "status": "Arrived",
    "cross_street": "",
    "nearest_intersection": "West Grace Street",
    "location_township": "Precinct 4",
    "lat": 37.551079,
    "lng": -77.453249
  },
  {
    "type_general": "RPD",
    "dispatch_time": "12/16/2025 13:29",
    "box_no": "Precinct 3",
    "type_specific": "D.O.A. , INVESTIGATE",
    "street": "900-BLK DUNBAR ST",
    "status": "Enroute",
    "cross_street": "",
    "nearest_intersection": "",
    "location_township": "Precinct 3",
    "lat": null,
    "lng": null
  },
  {
    "type_general": "RPD",
    "dispatch_time": "12/16/2025 13:32",
    "box_no": "Precinct 3",
    "type_specific": "MENTAL SUBJECT , MENTAL SUBJECT EMERGENT",
    "street": "6300-BLK JAHNKE RD",
    "status": "Arrived",
    "cross_street": "",
    "nearest_intersection": "",
    "location_township": "Precinct 3",
    "lat": null,
    "lng": null
  },
  {
    "type_general": "RPD",
    "dispatch_time": "12/16/2025 13:37",
    "box_no": "Precinct 3",
    "type_specific": "ASSIST FIRE DEPARTMENT , TRAFFIC AND/OR CROWD CONTROL",
    "street": "3300-BLK CHEVERLY RD",
    "status": "Enroute",
    "cross_street": "",
    "nearest_intersection": "",
    "location_township": "Precinct 3",
    "lat": null,
    "lng": null
  },
  {
    "type_general": "RPD",
    "dispatch_time": "12/16/2025 13:42",
    "box_no": "Precinct 2",
    "type_specific": "ASSIST - OTHER AGENCY OR CALLER , OTHER AGENCY OR DEPARTMENT",
    "street": "1400-BLK CLARKSON RD",
    "status": "Dispatched",
    "cross_street": "",
    "nearest_intersection": "",
    "location_township": "Precinct 2",
    "lat": null,
    "lng": null
  },
  {
    "type_general": "RFD",
    "dispatch_time": "12/16/2025 12:07",
    "box_no": "FIRE",
    "type_specific": "# STRUCTURE FIRE , HOUSE FIRE",
    "street": "2500-BLK TITUS ST",
    "status": "Arrived",
    "cross_street": "",
    "nearest_intersection": "",
    "location_township": "FIRE",
    "lat": null,
    "lng": null
  },
  {
    "type_general": "RFD",
    "dispatch_time": "12/16/2025 13:37",
    "box_no": "FIRE",
    "type_specific": "# VEHICLE FIRE , CAR OR PICKUP",
    "street": "3300-BLK CHEVERLY RD",
    "status": "Arrived",
    "cross_street": "",
    "nearest_intersection": "",
    "location_township": "FIRE",
    "lat": null,
    "lng": null
  },
  {
    "type_general": "RFD",
    "dispatch_time": "12/16/2025 13:47",
    "box_no": "FIRE",
    "type_specific": "# FIRE ALARM , CARBON MONOXIDE",
    "street": "1700-BLK 3RD AVE",
    "status": "Arrived",
    "cross_street": "",
    "nearest_intersection": "",
    "location_township": "FIRE",
    "lat": null,
    "lng": null
  }
]