[
  {
    "type_general": "RPD",
    "dispatch_time": "12/09/2025 05:29",
    "box_no": "Precinct 1",
    "type_specific": "SUSPICIOUS , PERSON",
    "street": "1800-BLK INGRAM AVE",
    "status": "Enroute",
    "cross_street": "",
    "nearest_intersection": "Ingram Avenue",
    "location_township": "Precinct 1",
    "lat": 37.5075283,
    "lng": -77.4395561
  },
  {
    "type_general": "RPD",
    "dispatch_time": "12/09/2025 05:59",
    "box_no": "Precinct 1",
    "type_specific": "BURGLAR ALARM , INVESTIGATE",
    "street": "1600-BLK NATIONAL ST",
    "status": "Enroute",
    "cross_street": "",
    "nearest_intersection": "National Street",
    "location_township": "Precinct 1",
    "lat": 37.5156527,
    "lng": -77.3964186
  },
  {
    "type_general": "RPD",
    "dispatch_time": "12/09/2025 06:14",
    "box_no": "Precinct 1",
    "type_specific": "DOMESTIC TROUBLE , INVESTIGATE",
    "street": "700-BLK MOSBY ST",
    "status": "Arrived",
    "cross_street": "",
    "nearest_intersection": "Mosby Street",
    "location_township": "Precinct 1",
    "lat": 37.5387652,
    "lng": -77.4207419
  },
  {
    "type_general": "RFD",
    "dispatch_time": "12/09/2025 06:41",
    "box_no": "FIRE",
    "type_specific": "# ASSIST EMS , LIFTING ASSISTANCE",
    "street": "1900-BLK RAVEN ST",
    "status": "Arrived",
    "cross_street": "",
    "nearest_intersection": "Raven Street",
    "location_township": "FIRE",
    "lat": 37.549938,
    "lng": -77.421725
  }
]