[
  {
    "type_general": "RPD",
    "dispatch_time": "12/12/2025 08:59",
    "box_no": "Precinct 4",
    "type_specific": "LOST PROPERTY , DPR CALL - TAKE A REPORT",
    "street": "1800-BLK HIGHPOINT AVE",
    "status": "Arrived",
    "cross_street": "",
    "nearest_intersection": "Highpoint Avenue",
    "location_township": "Precinct 4",
    "lat": 37.570312,
    "lng": -77.469224
  },
  {
    "type_general": "RPD",
    "dispatch_time": "12/12/2025 09:05",
    "box_no": "Precinct 3",
    "type_specific": "DRUG/NARCOTICS OFFENSE , INVESTIGATE / OUTSIDE - EMS",
    "street": "3500-BLK ELLWOOD AVE",
    "status": "Arrived",
    "cross_street": "",
    "nearest_intersection": "Ellwood Avenue",
    "location_township": "Precinct 3",
    "lat": 37.556473,
    "lng": -77.486031
  },
  {
    "type_general": "RPD",
    "dispatch_time": "12/12/2025 09:25",
    "box_no": "Precinct 1",
    "type_specific": "ASSIST - OTHER AGENCY OR CALLER , OTHER AGENCY OR DEPARTMENT",
    "street": "900-BLK HULL ST",
    "status": "Enroute",
    "cross_street": "",
    "nearest_intersection": "Hull Street",
    "location_township": "Precinct 1",
    "lat": 37.522337,
    "lng": -77.441729
  },
  {
    "type_general": "RPD",
    "dispatch_time": "12/12/2025 09:28",
    "box_no": "DPR",
    "type_specific": "LARCENY , DPR Call - Take a Report",
    "street": "1800-BLK MACTAVISH AVE",
    "status": "Dispatched",
    "cross_street": "",
    "nearest_intersection": "Mactavish Avenue",
    "location_township": "DPR",
    "lat": 37.5713371,
    "lng": -77.4703301
  },
  {
    "type_general": "RPD",
    "dispatch_time": "12/12/2025 09:48",
    "box_no": "Precinct 3",
    "type_specific": "FOUND PROPERTY , INVESTIGATE",
    "street": "300-BLK S MEADOW ST",
    "status": "Enroute",
    "cross_street": "",
    "nearest_intersection": "South Meadow Street",
    "location_township": "Precinct 3",
    "lat": 37.5448002,
    "lng": -77.4682238
  },
  {
    "type_general": "RPD",
    "dispatch_time": "12/12/2025 10:12",
    "box_no": "Precinct 1",
    "type_specific": "PARKING COMPLAINT , INVESTIGATE",
    "street": "2100-BLK SELDEN ST",
    "status": "Arrived",
    "cross_street": "",
    "nearest_intersection": "Selden Street",
    "location_township": "Precinct 1",
    "lat": 37.5502101,
    "lng": -77.4076761
  },
  {
    "type_general": "RPD",
    "dispatch_time": "12/12/2025 10:14",
    "box_no": "Precinct 4",
    "type_specific": "MENTAL SUBJECT , INVESTIGATE EMS",
    "street": "3400-BLK W CLAY ST",
    "status": "Arrived",
    "cross_street": "",
    "nearest_intersection": "West Clay Street",
    "location_township": "Precinct 4",
    "lat": 37.5694404,
    "lng": -77.4748981
  },
  {
    "type_general": "RPD",
    "dispatch_time": "12/12/2025 10:16",
    "box_no": "Precinct 4",
    "type_specific": "DOMESTIC TROUBLE , VIOLENT",
    "street": "900-BLK SLEDD ST",
    "status": "Arrived",
    "cross_street": "",
    "nearest_intersection": "Sledd Street, Northside",
    "location_township": "Precinct 4",
    "lat": 37.557176,
    "lng": -77.446604
  },
  {
    "type_general": "RPD",
    "dispatch_time": "12/12/2025 10:22",
    "box_no": "Precinct 4",
    "type_specific": "BURGLAR ALARM , INVESTIGATE",
    "street": "100-BLK GOVERNOR ST",
    "status": "Enroute",
    "cross_street": "",
    "nearest_intersection": "Bank Street",
    "location_township": "Precinct 4",
    "lat": 37.536975,
    "lng": -77.432601
  },
  {
    "type_general": "RPD",
    "dispatch_time": "12/12/2025 10:31",
    "box_no": "Precinct 1",
    "type_specific": "DOMESTIC TROUBLE , INVESTIGATE",
    "street": "2200-BLK CREIGHTON RD",
    "status": "Arrived",
    "cross_street": "",
    "nearest_intersection": "Creighton Road",
    "location_township": "Precinct 1",
    "lat": 37.545519,
    "lng": -77.398135
  },
  {
    "type_general": "RFD",
    "dispatch_time": "12/12/2025 09:03",
    "box_no": "FIRE",
    "type_specific": "# STRUCTURE FIRE , HOUSE FIRE",
    "street": "3000-BLK ARCHDALE RD",
    "status": "Arrived",
    "cross_street": "",
    "nearest_intersection": "Archdale Road",
    "location_township": "FIRE",
    "lat": 37.539231,
    "lng": -77.545258
  },
  {
    "type_general": "RFD",
    "dispatch_time": "12/12/2025 09:56",
    "box_no": "FIRE",
    "type_specific": "# FIRE STANDBY , VENUE",
    "street": "0-BLK N LAUREL ST",
    "status": "Dispatched",
    "cross_street": "",
    "nearest_intersection": "North Laurel Street",
    "location_township": "FIRE",
    "lat": 37.5465072,
    "lng": -77.4515552
  },
  {
    "type_general": "RFD",
    "dispatch_time": "12/12/2025 09:56",
    "box_no": "FIRE",
    "type_specific": "# FIRE STANDBY , VENUE",
    "street": "0-BLK N LAUREL ST",
    "status": "Arrived",
    "cross_street": "",
    "nearest_intersection": "North Laurel Street",
    "location_township": "FIRE",
    "lat": 37.5465072,
    "lng": -77.4515552
  },
  {
    "type_general": "RPD",
    "dispatch_time": "12/12/2025 10:35",
    "box_no": "Precinct 1",
    "type_specific": "UNNECESSARY NOISE , INVESTIGATE",
    "street": "1600-BLK MAURY ST",
    "status": "Arrived",
    "cross_street": "",
    "nearest_intersection": "Maury Street, Southside",
    "location_township": "Precinct 1",
    "lat": 37.5151725,
    "lng": -77.4441974
  },
  {
    "type_general": "RPD",
    "dispatch_time": "12/12/2025 10:48",
    "box_no": "Precinct 4",
    "type_specific": "MISSING PERSON - AT RISK , INVESTIGATE",
    "street": "1600-BLK 4TH AVE",
    "status": "Enroute",
    "cross_street": "",
    "nearest_intersection": "4th Avenue, Northside",
    "location_township": "Precinct 4",
    "lat": 37.556334,
    "lng": -77.425946
  },
  {
    "type_general": "RPD",
    "dispatch_time": "12/12/2025 10:53",
    "box_no": "Precinct 4",
    "type_specific": "TRAFFIC STOP , OFFICER-INITIATED",
    "street": "600-BLK CUMBERLAND ST",
    "status": "Dispatched",
    "cross_street": "",
    "nearest_intersection": "South Belvidere Street",
    "location_township": "Precinct 4",
    "lat": 37.543224,
    "lng": -77.449269
  },
  {
    "type_general": "RPD",
    "dispatch_time": "12/12/2025 10:53",
    "box_no": "Precinct 4",
    "type_specific": "TRAFFIC STOP , OFFICER-INITIATED",
    "street": "600-BLK CUMBERLAND ST",
    "status": "Arrived",
    "cross_street": "",
    "nearest_intersection": "South Belvidere Street",
    "location_township": "Precinct 4",
    "lat": 37.543224,
    "lng": -77.449269
  },
  {
    "type_general": "RPD",
    "dispatch_time": "12/12/2025 10:43",
    "box_no": "Precinct 1",
    "type_specific": "DISORDERLY , INVESTIGATE",
    "street": "1200-BLK N 35TH ST",
    "status": "Arrived",
    "cross_street": "",
    "nearest_intersection": "R Street, East End",
    "location_township": "Precinct 1",
    "lat": 37.532881,
    "lng": -77.401451
  },
  {
    "type_general": "RPD",
    "dispatch_time": "12/12/2025 11:02",
    "box_no": "DPR",
    "type_specific": "STOLEN VEHICLE , TAKE A REPORT (Field Unit Required)",
    "street": "6200-BLK JAHNKE RD",
    "status": "Enroute",
    "cross_street": "",
    "nearest_intersection": "Jahnke Road",
    "location_township": "DPR",
    "lat": 37.5205385,
    "lng": -77.510489
  },
  {
    "type_general": "RPD",
    "dispatch_time": "12/12/2025 10:46",
    "box_no": "DPR",
    "type_specific": "LARCENY , DPR Call - Take a Report",
    "street": "500-BLK W 19TH ST",
    "status": "Enroute",
    "cross_street": "",
    "nearest_intersection": "West 19th Street",
    "location_township": "DPR",
    "lat": 37.523018,
    "lng": -77.452975
  },
  {
    "type_general": "RFD",
    "dispatch_time": "12/12/2025 11:03",
    "box_no": "FIRE",
    "type_specific": "# EMS - 1ST RESP CALL (FIRE RESP ONLY) , CARDIAC/RESPIRATORY ARREST",
    "street": "1700-BLK BELLEVUE AVE",
    "status": "Arrived",
    "cross_street": "",
    "nearest_intersection": "Bellevue Avenue",
    "location_township": "FIRE",
    "lat": 37.590597,
    "lng": -77.464322
  },
  {
    "type_general": "RPD",
    "dispatch_time": "12/12/2025 10:38",
    "box_no": "Precinct 1",
    "type_specific": "MENTAL SUBJECT , MENTAL SUBJECT EMERGENT",
    "street": "1700-BLK N 28TH ST",
    "status": "Enroute",
    "cross_street": "",
    "nearest_intersection": "North 28th Street",
    "location_township": "Precinct 1",
    "lat": 37.5422553,
    "lng": -77.4046343
  },
  {
    "type_general": "RPD",
    "dispatch_time": "12/12/2025 10:36",
    "box_no": "Precinct 4",
    "type_specific": "WANTED PERSON , INVESTIGATE",
    "street": "7100-BLK JAHNKE RD",
    "status": "Arrived",
    "cross_street": "",
    "nearest_intersection": "Jahnke Road",
    "location_township": "Precinct 4",
    "lat": 37.516009,
    "lng": -77.525109
  }
]