[
  {
    "type_general": "RPD",
    "dispatch_time": "12/13/2025 01:53",
    "box_no": "Precinct 3",
    "type_specific": "MENTAL SUBJECT , TDO / ECO",
    "street": "7100-BLK JAHNKE RD",
    "status": "Arrived",
    "cross_street": "",
    "nearest_intersection": "Jahnke Road",
    "location_township": "Precinct 3",
    "lat": 37.516009,
    "lng": -77.525109
  },
  {
    "type_general": "RPD",
    "dispatch_time": "12/14/2025 22:06",
    "box_no": "Precinct 2",
    "type_specific": "MENTAL SUBJECT , TDO / ECO",
    "street": "400-BLK W RANDOLPH RD",
    "status": "Arrived",
    "cross_street": "",
    "nearest_intersection": "",
    "location_township": "Precinct 2",
    "lat": null,
    "lng": null
  },
  {
    "type_general": "RPD",
    "dispatch_time": "12/15/2025 08:11",
    "box_no": "Precinct 3",
    "type_specific": "TRAFFIC COMPLAINT , INVESTIGATE",
    "street": "SCHOOL ZONE",
    "status": "Dispatched",
    "cross_street": "",
    "nearest_intersection": "",
    "location_township": "Precinct 3",
    "lat": null,
    "lng": null
  },
  {
    "type_general": "RPD",
    "dispatch_time": "12/15/2025 08:11",
    "box_no": "Precinct 3",
    "type_specific": "TRAFFIC COMPLAINT , INVESTIGATE",
    "street": "SCHOOL ZONE",
    "status": "Arrived",
    "cross_street": "",
    "nearest_intersection": "",
    "location_township": "Precinct 3",
    "lat": null,
    "lng": null
  },
  {
    "type_general": "RPD",
    "dispatch_time": "12/15/2025 07:43",
    "box_no": "Precinct 2",
    "type_specific": "DOMESTIC TROUBLE , VIOLENT",
    "street": "1500-BLK LYNHAVEN AVE",
    "status": "Arrived",
    "cross_street": "",
    "nearest_intersection": "Lynhaven Avenue",
    "location_township": "Precinct 2",
    "lat": 37.499317,
    "lng": -77.442343
  },
  {
    "type_general": "RPD",
    "dispatch_time": "12/15/2025 08:19",
    "box_no": "Precinct 2",
    "type_specific": "DOMESTIC TROUBLE , INVESTIGATE - EMS",
    "street": "1500-BLK CLARKSON RD",
    "status": "Arrived",
    "cross_street": "",
    "nearest_intersection": "Clarkson Road, Southside",
    "location_township": "Precinct 2",
    "lat": 37.4952595,
    "lng": -77.4785319
  },
  {
    "type_general": "RPD",
    "dispatch_time": "12/15/2025 07:51",
    "box_no": "Precinct 4",
    "type_specific": "BREAK & ENTER , INVESTIGATE",
    "street": "1000-BLK FOURQUREAN LN",
    "status": "Arrived",
    "cross_street": "",
    "nearest_intersection": "Fourqurean Lane, Northside",
    "location_township": "Precinct 4",
    "lat": 37.5686638,
    "lng": -77.4250346
  },
  {
    "type_general": "RPD",
    "dispatch_time": "12/15/2025 08:55",
    "box_no": "Precinct 2",
    "type_specific": "ABANDONED VEHICLE , INVESTIGATE",
    "street": "400-BLK W 33RD ST",
    "status": "Arrived",
    "cross_street": "",
    "nearest_intersection": "West 33rd Street",
    "location_township": "Precinct 2",
    "lat": 37.5155908,
    "lng": -77.4676648
  },
  {
    "type_general": "RPD",
    "dispatch_time": "12/15/2025 08:53",
    "box_no": "Precinct 4",
    "type_specific": "DOMESTIC TROUBLE , VIOLENT - EMS",
    "street": "2000-BLK BROOK RD",
    "status": "Arrived",
    "cross_street": "",
    "nearest_intersection": "Bath Street, Northside",
    "location_township": "Precinct 4",
    "lat": 37.5608096,
    "lng": -77.4479214
  },
  {
    "type_general": "RPD",
    "dispatch_time": "12/15/2025 08:20",
    "box_no": "Precinct 4",
    "type_specific": "DOMESTIC TROUBLE , INVESTIGATE",
    "street": "3600-BLK CHAMBERLAYNE AVE",
    "status": "Arrived",
    "cross_street": "",
    "nearest_intersection": "Walton Avenue, Northside",
    "location_township": "Precinct 4",
    "lat": 37.581665,
    "lng": -77.446998
  },
  {
    "type_general": "RPD",
    "dispatch_time": "12/15/2025 09:23",
    "box_no": "Precinct 4",
    "type_specific": "DOMESTIC TROUBLE , INVESTIGATE",
    "street": "100-BLK W BROAD ST",
    "status": "Arrived",
    "cross_street": "",
    "nearest_intersection": "West Broad Street",
    "location_township": "Precinct 4",
    "lat": 37.5464347,
    "lng": -77.4427708
  },
  {
    "type_general": "RPD",
    "dispatch_time": "12/15/2025 09:29",
    "box_no": "Precinct 1",
    "type_specific": "IN-PROGRESS (Assault or battery by mob) , IN-PROGRESS- EMS",
    "street": "500-BLK BAINBRIDGE ST",
    "status": "Arrived",
    "cross_street": "",
    "nearest_intersection": "Bainbridge Street",
    "location_township": "Precinct 1",
    "lat": 37.5249709,
    "lng": -77.4395966
  },
  {
    "type_general": "RPD",
    "dispatch_time": "12/15/2025 09:43",
    "box_no": "Precinct 2",
    "type_specific": "ASSIST FIRE DEPARTMENT , TRAFFIC AND/OR CROWD CONTROL",
    "street": "500-BLK E SOUTHSIDE PLZ",
    "status": "Arrived",
    "cross_street": "",
    "nearest_intersection": "East Belt Boulevard, Southside",
    "location_township": "Precinct 2",
    "lat": 37.5043742,
    "lng": -77.4751373
  },
  {
    "type_general": "RPD",
    "dispatch_time": "12/15/2025 08:59",
    "box_no": "Precinct 1",
    "type_specific": "FOUND PROPERTY , INVESTIGATE",
    "street": "1300-BLK SEMMES AVE",
    "status": "Enroute",
    "cross_street": "",
    "nearest_intersection": "Semmes Avenue",
    "location_township": "Precinct 1",
    "lat": 37.5244096,
    "lng": -77.4490873
  },
  {
    "type_general": "RPD",
    "dispatch_time": "12/15/2025 09:06",
    "box_no": "DPR",
    "type_specific": "SUSPICIOUS , INVESTIGATE",
    "street": "300-BLK W CHARITY ST",
    "status": "Arrived",
    "cross_street": "",
    "nearest_intersection": "West Charity Street",
    "location_township": "DPR",
    "lat": 37.5525386,
    "lng": -77.4393965
  },
  {
    "type_general": "RPD",
    "dispatch_time": "12/15/2025 09:50",
    "box_no": "Precinct 3",
    "type_specific": "PARKING COMPLAINT , INVESTIGATE",
    "street": "00-BLK S DOOLEY AVE",
    "status": "Arrived",
    "cross_street": "",
    "nearest_intersection": "South Dooley Avenue",
    "location_township": "Precinct 3",
    "lat": 37.5544942,
    "lng": -77.4837024
  },
  {
    "type_general": "RPD",
    "dispatch_time": "12/15/2025 09:53",
    "box_no": "Precinct 3",
    "type_specific": "CRASH , PROPERTY DAMAGE",
    "street": "JAHNKE RD/IRBY DR RICH",
    "status": "Arrived",
    "cross_street": "",
    "nearest_intersection": "Jahnke Road",
    "location_township": "Precinct 3",
    "lat": 37.5192018,
    "lng": -77.5169988
  },
  {
    "type_general": "RPD",
    "dispatch_time": "12/15/2025 10:09",
    "box_no": "Precinct 2",
    "type_specific": "ASSIST - OTHER AGENCY OR CALLER , CITIZEN",
    "street": "4100-BLK CASTLEWOOD RD",
    "status": "Arrived",
    "cross_street": "",
    "nearest_intersection": "Castlewood Road",
    "location_township": "Precinct 2",
    "lat": 37.4700931,
    "lng": -77.4457163
  },
  {
    "type_general": "RPD",
    "dispatch_time": "12/15/2025 10:21",
    "box_no": "Precinct 4",
    "type_specific": "ASSIST FIRE DEPARTMENT , TRAFFIC AND/OR CROWD CONTROL",
    "street": "3800-BLK W BROAD ST",
    "status": "Arrived",
    "cross_street": "",
    "nearest_intersection": "West Broad Street",
    "location_township": "Precinct 4",
    "lat": 37.5706416,
    "lng": -77.4793298
  },
  {
    "type_general": "RPD",
    "dispatch_time": "12/15/2025 10:32",
    "box_no": "Precinct 4",
    "type_specific": "TRAFFIC STOP , OFFICER-INITIATED",
    "street": "300-BLK S BELVIDERE ST",
    "status": "Dispatched",
    "cross_street": "",
    "nearest_intersection": "Floyd Avenue",
    "location_township": "Precinct 4",
    "lat": 37.5450741,
    "lng": -77.4489075
  },
  {
    "type_general": "RPD",
    "dispatch_time": "12/15/2025 10:32",
    "box_no": "Precinct 4",
    "type_specific": "TRAFFIC STOP , OFFICER-INITIATED",
    "street": "300-BLK S BELVIDERE ST",
    "status": "Arrived",
    "cross_street": "",
    "nearest_intersection": "Floyd Avenue",
    "location_township": "Precinct 4",
    "lat": 37.5450741,
    "lng": -77.4489075
  },
  {
    "type_general": "RPD",
    "dispatch_time": "12/15/2025 10:06",
    "box_no": "Precinct 4",
    "type_specific": "CRASH , PERSONAL INJURY",
    "street": "3400-BLK 2ND AVE",
    "status": "Arrived",
    "cross_street": "",
    "nearest_intersection": "2nd Avenue",
    "location_township": "Precinct 4",
    "lat": 37.5750447,
    "lng": -77.4144722
  },
  {
    "type_general": "RFD",
    "dispatch_time": "12/15/2025 10:25",
    "box_no": "FIRE",
    "type_specific": "# UTILITY INCIDENT , WATER RELATED",
    "street": "200-BLK S ARTHUR ASHE BLVD",
    "status": "Arrived",
    "cross_street": "",
    "nearest_intersection": "Downtown Expressway",
    "location_township": "FIRE",
    "lat": 37.5488772,
    "lng": -77.4777879
  },
  {
    "type_general": "RPD",
    "dispatch_time": "12/15/2025 10:31",
    "box_no": "Precinct 3",
    "type_specific": "TRESPASSING , INVESTIGATE",
    "street": "2300-BLK ROSEWOOD AVE",
    "status": "Enroute",
    "cross_street": "",
    "nearest_intersection": "Rosewood Avenue",
    "location_township": "Precinct 3",
    "lat": 37.5465718,
    "lng": -77.4719216
  },
  {
    "type_general": "RPD",
    "dispatch_time": "12/15/2025 10:35",
    "box_no": "Precinct 1",
    "type_specific": "DOMESTIC TROUBLE , INVESTIGATE",
    "street": "2300-BLK AMBROSE ST",
    "status": "Enroute",
    "cross_street": "",
    "nearest_intersection": "Ambrose Street",
    "location_township": "Precinct 1",
    "lat": 37.5546,
    "lng": -77.418318
  },
  {
    "type_general": "RPD",
    "dispatch_time": "12/15/2025 10:36",
    "box_no": "Precinct 1",
    "type_specific": "TRESPASSING , INVESTIGATE",
    "street": "1800-BLK JOPLIN AVE",
    "status": "Enroute",
    "cross_street": "",
    "nearest_intersection": "Joplin Avenue",
    "location_township": "Precinct 1",
    "lat": 37.5067951,
    "lng": -77.4388119
  },
  {
    "type_general": "RPD",
    "dispatch_time": "12/15/2025 10:12",
    "box_no": "Precinct 2",
    "type_specific": "DOMESTIC TROUBLE , ASSIST OR STANDBY",
    "street": "3400-BLK RICHMOND HWY",
    "status": "Arrived",
    "cross_street": "",
    "nearest_intersection": "Richmond Highway",
    "location_township": "Precinct 2",
    "lat": 37.4694278,
    "lng": -77.4434296
  }
]