[
  {
    "type_general": "RPD",
    "dispatch_time": "11/23/2025 18:19",
    "box_no": "Precinct 3",
    "type_specific": "MENTAL SUBJECT , TDO / ECO",
    "street": "1400-BLK JOHNSTON WILLIS DR",
    "status": "Arrived",
    "cross_street": "",
    "nearest_intersection": "",
    "location_township": "Precinct 3",
    "lat": null,
    "lng": null
  },
  {
    "type_general": "RPD",
    "dispatch_time": "11/24/2025 02:47",
    "box_no": "Precinct 4",
    "type_specific": "MENTAL SUBJECT , TDO / ECO",
    "street": "1300-BLK E MARSHALL ST",
    "status": "Arrived",
    "cross_street": "",
    "nearest_intersection": "East Marshall Street",
    "location_township": "Precinct 4",
    "lat": 37.5396586,
    "lng": -77.4286204
  },
  {
    "type_general": "RPD",
    "dispatch_time": "11/24/2025 17:26",
    "box_no": "Precinct 1",
    "type_specific": "MENTAL SUBJECT , INVESTIGATE",
    "street": "3700-BLK CRESTVIEW RD",
    "status": "Arrived",
    "cross_street": "",
    "nearest_intersection": "Crestview Road",
    "location_township": "Precinct 1",
    "lat": 37.5275125,
    "lng": -77.4051931
  },
  {
    "type_general": "RPD",
    "dispatch_time": "11/24/2025 18:18",
    "box_no": "Precinct 2",
    "type_specific": "PERSON DOWN , INVESTIGATE",
    "street": "1700-BLK CLARKSON RD",
    "status": "Arrived",
    "cross_street": "",
    "nearest_intersection": "Clarkson Road, Southside",
    "location_township": "Precinct 2",
    "lat": 37.4923295,
    "lng": -77.481047
  },
  {
    "type_general": "RPD",
    "dispatch_time": "11/24/2025 19:01",
    "box_no": "Precinct 4",
    "type_specific": "TRESPASSING , INVESTIGATE",
    "street": "00-BLK E BROOKLAND PARK BLVD",
    "status": "Arrived",
    "cross_street": "",
    "nearest_intersection": "East Brookland Park Boulevard",
    "location_township": "Precinct 4",
    "lat": 37.568967,
    "lng": -77.4167096
  },
  {
    "type_general": "RPD",
    "dispatch_time": "11/24/2025 20:11",
    "box_no": "Precinct 3",
    "type_specific": "CRASH , CITY PROPERTY",
    "street": "6800-BLK FOREST HILL AVE",
    "status": "Arrived",
    "cross_street": "",
    "nearest_intersection": "Forest Hill Avenue",
    "location_township": "Precinct 3",
    "lat": 37.538209,
    "lng": -77.520181
  },
  {
    "type_general": "RPD",
    "dispatch_time": "11/24/2025 20:13",
    "box_no": "Precinct 4",
    "type_specific": "SUSPICIOUS , PERSON",
    "street": "100-BLK W DUVAL ST",
    "status": "Arrived",
    "cross_street": "",
    "nearest_intersection": "West Duval Street",
    "location_township": "Precinct 4",
    "lat": 37.5505469,
    "lng": -77.4391577
  },
  {
    "type_general": "RPD",
    "dispatch_time": "11/24/2025 21:57",
    "box_no": "Precinct 1",
    "type_specific": "PERSON DOWN , INVESTIGATE",
    "street": "N 21ST ST/E MAIN ST RICH",
    "status": "Enroute",
    "cross_street": "",
    "nearest_intersection": "North 21st Street",
    "location_township": "Precinct 1",
    "lat": 37.5460125,
    "lng": -77.4108059
  },
  {
    "type_general": "RPD",
    "dispatch_time": "11/24/2025 22:13",
    "box_no": "Precinct 1",
    "type_specific": "ASSIST - OTHER AGENCY OR CALLER , OTHER AGENCY OR DEPARTMENT",
    "street": "1300-BLK N 37TH ST",
    "status": "Arrived",
    "cross_street": "",
    "nearest_intersection": "North 37th Street",
    "location_township": "Precinct 1",
    "lat": 37.5317596,
    "lng": -77.3986373
  },
  {
    "type_general": "RPD",
    "dispatch_time": "11/24/2025 22:15",
    "box_no": "Precinct 4",
    "type_specific": "FRAUD /FORGERY INCIDENT , INVESTIGATE",
    "street": "1100-BLK N 2ND ST",
    "status": "Enroute",
    "cross_street": "",
    "nearest_intersection": "North 2nd Street",
    "location_township": "Precinct 4",
    "lat": 37.5520175,
    "lng": -77.4334273
  },
  {
    "type_general": "RPD",
    "dispatch_time": "11/24/2025 22:29",
    "box_no": "Precinct 4",
    "type_specific": "CRASH , PROPERTY DAMAGE",
    "street": "CHAMBERLAYNE AVE/W BROOKLAND PARK BLVD RICH",
    "status": "Arrived",
    "cross_street": "",
    "nearest_intersection": "Chamberlayne Avenue, Northside",
    "location_township": "Precinct 4",
    "lat": 37.5845486,
    "lng": -77.4473886
  },
  {
    "type_general": "RPD",
    "dispatch_time": "11/24/2025 22:32",
    "box_no": "Precinct 2",
    "type_specific": "SUSPICIOUS , INVESTIGATE",
    "street": "3100-BLK GLENAN DR",
    "status": "Enroute",
    "cross_street": "",
    "nearest_intersection": "Glenan Drive",
    "location_township": "Precinct 2",
    "lat": 37.4751091,
    "lng": -77.4637419
  },
  {
    "type_general": "RFD",
    "dispatch_time": "11/24/2025 22:40",
    "box_no": "FIRE",
    "type_specific": "# EMS - 1ST RESP CALL (FIRE RESP ONLY) , UNKNOWN PROBLEM/PERSON DOWN",
    "street": "5600-BLK PETOSKEY AVE",
    "status": "Arrived",
    "cross_street": "",
    "nearest_intersection": "Petoskey Avenue",
    "location_township": "FIRE",
    "lat": 37.4988816,
    "lng": -77.5008037
  },
  {
    "type_general": "RPD",
    "dispatch_time": "11/24/2025 22:47",
    "box_no": "Precinct 4",
    "type_specific": "TRAFFIC STOP , OFFICER-INITIATED",
    "street": "3800-BLK NORTH AVE",
    "status": "Dispatched",
    "cross_street": "",
    "nearest_intersection": "North Avenue, Northside",
    "location_township": "Precinct 4",
    "lat": 37.582235,
    "lng": -77.4353969
  },
  {
    "type_general": "RPD",
    "dispatch_time": "11/24/2025 22:47",
    "box_no": "Precinct 4",
    "type_specific": "TRAFFIC STOP , OFFICER-INITIATED",
    "street": "3800-BLK NORTH AVE",
    "status": "Arrived",
    "cross_street": "",
    "nearest_intersection": "North Avenue, Northside",
    "location_township": "Precinct 4",
    "lat": 37.582235,
    "lng": -77.4353969
  },
  {
    "type_general": "RPD",
    "dispatch_time": "11/24/2025 22:43",
    "box_no": "Precinct 3",
    "type_specific": "DOMESTIC TROUBLE , INVESTIGATE",
    "street": "1100-BLK W MAIN ST",
    "status": "Arrived",
    "cross_street": "",
    "nearest_intersection": "West Main Street",
    "location_township": "Precinct 3",
    "lat": 37.5460193,
    "lng": -77.4554581
  },
  {
    "type_general": "RPD",
    "dispatch_time": "11/24/2025 22:42",
    "box_no": "Precinct 2",
    "type_specific": "DOMESTIC TROUBLE , INVESTIGATE",
    "street": "800-BLK RICHMOND HWY",
    "status": "Arrived",
    "cross_street": "",
    "nearest_intersection": "Richmond Highway",
    "location_township": "Precinct 2",
    "lat": 37.508793,
    "lng": -77.4480183
  }
]