[
  {
    "type_general": "RPD",
    "dispatch_time": "12/12/2025 09:25",
    "box_no": "Precinct 1",
    "type_specific": "ASSIST - OTHER AGENCY OR CALLER , OTHER AGENCY OR DEPARTMENT",
    "street": "900-BLK HULL ST",
    "status": "Arrived",
    "cross_street": "",
    "nearest_intersection": "Hull Street",
    "location_township": "Precinct 1",
    "lat": 37.522337,
    "lng": -77.441729
  },
  {
    "type_general": "RPD",
    "dispatch_time": "12/12/2025 11:11",
    "box_no": "Precinct 4",
    "type_specific": "D.O.A. , INVESTIGATE",
    "street": "1700-BLK BELLEVUE AVE",
    "status": "Arrived",
    "cross_street": "",
    "nearest_intersection": "Bellevue Avenue",
    "location_township": "Precinct 4",
    "lat": 37.590597,
    "lng": -77.464322
  },
  {
    "type_general": "RPD",
    "dispatch_time": "12/12/2025 11:18",
    "box_no": "Precinct 4",
    "type_specific": "SUSPICIOUS , INVESTIGATE",
    "street": "100-BLK W DUVAL ST",
    "status": "Arrived",
    "cross_street": "",
    "nearest_intersection": "West Duval Street",
    "location_township": "Precinct 4",
    "lat": 37.5505469,
    "lng": -77.4391577
  },
  {
    "type_general": "RPD",
    "dispatch_time": "12/12/2025 11:24",
    "box_no": "Precinct 2",
    "type_specific": "MENTAL SUBJECT , TDO / ECO",
    "street": "1400-BLK GREYSTONE AVE",
    "status": "Enroute",
    "cross_street": "",
    "nearest_intersection": "Greystone Avenue, Southside",
    "location_township": "Precinct 2",
    "lat": 37.4954807,
    "lng": -77.471603
  },
  {
    "type_general": "RPD",
    "dispatch_time": "12/12/2025 12:20",
    "box_no": "Precinct 1",
    "type_specific": "SEARCH WARRANT , INVESTIGATE",
    "street": "200-BLK W BROAD ST",
    "status": "Arrived",
    "cross_street": "",
    "nearest_intersection": "West Broad Street",
    "location_township": "Precinct 1",
    "lat": 37.547,
    "lng": -77.4435632
  },
  {
    "type_general": "RPD",
    "dispatch_time": "12/12/2025 12:39",
    "box_no": "Precinct 2",
    "type_specific": "BURGLAR ALARM , INVESTIGATE",
    "street": "2500-BLK SEMMES AVE",
    "status": "Arrived",
    "cross_street": "",
    "nearest_intersection": "Semmes Avenue",
    "location_township": "Precinct 2",
    "lat": 37.5198453,
    "lng": -77.458831
  },
  {
    "type_general": "RPD",
    "dispatch_time": "12/12/2025 12:42",
    "box_no": "Precinct 2",
    "type_specific": "WANTED PERSON , INVESTIGATE",
    "street": "2200-BLK CHALFONT DR",
    "status": "Dispatched",
    "cross_street": "",
    "nearest_intersection": "Chalfont Drive, Southside",
    "location_township": "Precinct 2",
    "lat": 37.4908816,
    "lng": -77.4654757
  },
  {
    "type_general": "RPD",
    "dispatch_time": "12/12/2025 12:53",
    "box_no": "DPR",
    "type_specific": "ASSIST - OTHER AGENCY OR CALLER",
    "street": "MECHANICSVILLE TPKE/MAGNOLIA ST RICH",
    "status": "Dispatched",
    "cross_street": "",
    "nearest_intersection": "Mechanicsville Turnpike",
    "location_township": "DPR",
    "lat": 37.5514699,
    "lng": -77.4128847
  },
  {
    "type_general": "RPD",
    "dispatch_time": "12/12/2025 13:02",
    "box_no": "Precinct 4",
    "type_specific": "ASSIST - OTHER AGENCY OR CALLER , OTHER AGENCY OR DEPARTMENT",
    "street": "100-BLK W CHARITY ST",
    "status": "Arrived",
    "cross_street": "",
    "nearest_intersection": "West Charity Street",
    "location_township": "Precinct 4",
    "lat": 37.55204,
    "lng": -77.437396
  },
  {
    "type_general": "RPD",
    "dispatch_time": "12/12/2025 13:03",
    "box_no": "DPR",
    "type_specific": "FRAUD /FORGERY INCIDENT , DPR Call - Take a Report",
    "street": "1900-BLK BELT BLVD",
    "status": "Arrived",
    "cross_street": "",
    "nearest_intersection": "Belt Boulevard, Southside",
    "location_township": "DPR",
    "lat": 37.4903204,
    "lng": -77.4694528
  },
  {
    "type_general": "RPD",
    "dispatch_time": "12/12/2025 13:09",
    "box_no": "Precinct 4",
    "type_specific": "PRISONER TRANSPORT , PRISONER TRANSPORT",
    "street": "200-BLK E BROAD ST",
    "status": "Dispatched",
    "cross_street": "",
    "nearest_intersection": "East Broad Street",
    "location_township": "Precinct 4",
    "lat": 37.5446393,
    "lng": -77.4398964
  },
  {
    "type_general": "RPD",
    "dispatch_time": "12/12/2025 13:09",
    "box_no": "Precinct 4",
    "type_specific": "PRISONER TRANSPORT , PRISONER TRANSPORT",
    "street": "200-BLK E BROAD ST",
    "status": "Arrived",
    "cross_street": "",
    "nearest_intersection": "East Broad Street",
    "location_township": "Precinct 4",
    "lat": 37.5446393,
    "lng": -77.4398964
  },
  {
    "type_general": "RPD",
    "dispatch_time": "12/12/2025 13:13",
    "box_no": "Precinct 2",
    "type_specific": "TRAFFIC STOP , OFFICER-INITIATED",
    "street": "BELT BLVD/STOCKTON ST RICH",
    "status": "Arrived",
    "cross_street": "",
    "nearest_intersection": "Belt Boulevard, Southside",
    "location_township": "Precinct 2",
    "lat": 37.4819006,
    "lng": -77.4619128
  },
  {
    "type_general": "RPD",
    "dispatch_time": "12/12/2025 13:08",
    "box_no": "Precinct 1",
    "type_specific": "ASSAULT , INVESTIGATE",
    "street": "100-BLK N 18TH ST",
    "status": "Arrived",
    "cross_street": "",
    "nearest_intersection": "East Franklin Street",
    "location_township": "Precinct 1",
    "lat": 37.533922,
    "lng": -77.426799
  }
]